README.txt
pylons_gaq.py
setup.cfg
setup.py
pylons_gaq.egg-info/PKG-INFO
pylons_gaq.egg-info/SOURCES.txt
pylons_gaq.egg-info/dependency_links.txt
pylons_gaq.egg-info/not-zip-safe
pylons_gaq.egg-info/requires.txt
pylons_gaq.egg-info/top_level.txt